sample/__init__.py
sample/package_data.dat
sample/simple.py
mahadevadd-3.0.0.dist-info/LICENSE.txt
mahadevadd-3.0.0.dist-info/METADATA
mahadevadd-3.0.0.dist-info/WHEEL
mahadevadd-3.0.0.dist-info/entry_points.txt
mahadevadd-3.0.0.dist-info/top_level.txt
mahadevadd-3.0.0.dist-info/RECORD
