Metadata-Version: 2.1
Name: mahadevadd
Version: 3.0.0
Summary: A sample Python project
Author: mahadev_ajagalla
License: MIT License
Project-URL: Homepage, https://github.com/pypa/sampleproject
Project-URL: Bug Reports, https://github.com/pypa/sampleproject/issues
Project-URL: Funding, https://donate.pypi.org
Project-URL: Say Thanks!, http://saythanks.io/to/example
Project-URL: Source, https://github.com/pypa/sampleproject/
Keywords: sample,setuptools,development
Classifier: Development Status :: 3 - Alpha
Classifier: Intended Audience :: Developers
Classifier: Topic :: Software Development :: Build Tools
Classifier: License :: OSI Approved :: MIT License
Classifier: Programming Language :: Python :: 3
Classifier: Programming Language :: Python :: 3.7
Classifier: Programming Language :: Python :: 3.8
Classifier: Programming Language :: Python :: 3.9
Classifier: Programming Language :: Python :: 3.10
Classifier: Programming Language :: Python :: 3.11
Classifier: Programming Language :: Python :: 3 :: Only
Requires-Python: >=3.7
License-File: LICENSE.txt
Requires-Dist: peppercorn
Provides-Extra: dev
Requires-Dist: check-manifest ; extra == 'dev'
Provides-Extra: test
Requires-Dist: coverage ; extra == 'test'
